{
  "interests": [
    {
      "link": "https://anilist.co/user/ImRay/",
      "label": "My AniList",
      "icon": "fluent:animal-cat-24-regular"
    },
    {
      "link": "https://open.spotify.com/user/s4i5cqkyu7n068b7f5139sl7m?si=kMeKkWd0TK-_wfRaPyeHow",
      "label": "Playlists",
      "icon": "tabler:brand-spotify"
    },
    {
      "link": "https://goodreads.com/rayshold",
      "label": "Books",
      "icon": "tabler:bookmarks"
    },
    {
      "link": "https://trakt.tv/users/imray",
      "label": "Movies & Shows",
      "icon": "ri:movie-2-line"
    }
  ],
  "others": [
    {
      "link": "https://telegram.me/unikwalls",
      "label": "Walls stash",
      "icon": "tabler:photo"
    }
  ]
}
